graphene_django_subscriptions/__init__.py
graphene_django_subscriptions/bindings.py
graphene_django_subscriptions/consumers.py
graphene_django_subscriptions/middleware.py
graphene_django_subscriptions/mixins.py
graphene_django_subscriptions/subscription.py
graphene_django_subscriptions-0.0.9.dist-info/LICENSE
graphene_django_subscriptions-0.0.9.dist-info/METADATA
graphene_django_subscriptions-0.0.9.dist-info/WHEEL
graphene_django_subscriptions-0.0.9.dist-info/top_level.txt
graphene_django_subscriptions-0.0.9.dist-info/RECORD
