Metadata-Version: 2.1
Name: graphene-django-subscriptions
Version: 0.0.9
Summary: Graphene-Django-Subscriptions add subscriptions support to graphene-django through Channels module
Home-page: https://github.com/eamigo86/graphene-django-subscriptions
Author: Ernesto Perez Amigo
Author-email: eamigop86@gmail.com
License: MIT
Keywords: api graphql subscription rest graphene django channels
Platform: any
Classifier: Intended Audience :: Developers
Classifier: Topic :: Software Development :: Libraries
Classifier: Programming Language :: Python :: 2
Classifier: Programming Language :: Python :: 2.7
Classifier: Programming Language :: Python :: 3
Classifier: Programming Language :: Python :: 3.3
Classifier: Programming Language :: Python :: 3.4
Classifier: Programming Language :: Python :: 3.5
Classifier: Programming Language :: Python :: 3.6
Classifier: Programming Language :: Python :: 3.7
Classifier: Programming Language :: Python :: 3.8
Classifier: Programming Language :: Python :: Implementation :: PyPy
Requires-Dist: graphene-django (>=2.0.0)
Requires-Dist: graphene-django-extras (>=0.4.8)
Requires-Dist: channels-api (>=0.4.1)
